moku/__init__.py
moku/cli.py
moku/exceptions.py
moku/finder.py
moku/logging.py
moku/session.py
moku/utilities.py
moku/version.py
moku/instruments/__init__.py
moku/instruments/_awg.py
moku/instruments/_custominstrument.py
moku/instruments/_datalogger.py
moku/instruments/_digitalfilterbox.py
moku/instruments/_firfilter.py
moku/instruments/_fra.py
moku/instruments/_gs.py
moku/instruments/_laserlockbox.py
moku/instruments/_lockinamp.py
moku/instruments/_logicanalyzer.py
moku/instruments/_mim.py
moku/instruments/_nn.py
moku/instruments/_oscilloscope.py
moku/instruments/_phasemeter.py
moku/instruments/_pidcontroller.py
moku/instruments/_spectrumanalyzer.py
moku/instruments/_stream.py
moku/instruments/_tfa.py
moku/instruments/_waveformgenerator.py
moku/nn/__init__.py
moku/nn/_linn.py
moku-4.1.2.1.dist-info/METADATA
moku-4.1.2.1.dist-info/WHEEL
moku-4.1.2.1.dist-info/entry_points.txt
moku-4.1.2.1.dist-info/licenses/LICENSE.txt
moku-4.1.2.1.dist-info/RECORD
