Metadata-Version: 2.4
Name: moku
Version: 4.1.2.1
Summary: Python scripting interface to the Liquid Instruments Moku hardware
Project-URL: Homepage, https://liquidinstruments.com
Project-URL: Documentation, https://apis.liquidinstruments.com
Project-URL: Issues, https://www.liquidinstruments.com/support/contact/
Author-email: Liquid Instruments <info@liquidinstruments.com>
License: MIT
License-File: LICENSE.txt
Keywords: equipment,lab,liquid instruments,measurement,moku,mokugo,mokupro,test
Classifier: Development Status :: 5 - Production/Stable
Classifier: Intended Audience :: Developers
Classifier: Intended Audience :: Science/Research
Classifier: License :: OSI Approved :: MIT License
Classifier: Programming Language :: Python :: 3
Classifier: Programming Language :: Python :: 3.8
Classifier: Programming Language :: Python :: 3.9
Classifier: Programming Language :: Python :: 3.10
Classifier: Programming Language :: Python :: 3.11
Classifier: Programming Language :: Python :: 3.12
Classifier: Programming Language :: Python :: 3.13
Requires-Python: >=3.8
Requires-Dist: packaging>=20.0
Requires-Dist: requests<3.0,>=2.0
Requires-Dist: zeroconf>=0.47.0
Provides-Extra: neuralnetwork
Requires-Dist: numpy>=1.19.3; (python_version >= '3.9') and extra == 'neuralnetwork'
Requires-Dist: tensorflow>=2.17; (python_version >= '3.9') and extra == 'neuralnetwork'
